cspyce-2.3.2.dist-info/LICENSE.md
cspyce-2.3.2.dist-info/RECORD
cspyce-2.3.2.dist-info/WHEEL
cspyce-2.3.2.dist-info/top_level.txt
cspyce-2.3.2.dist-info/METADATA
cspyce/arrays.py
cspyce/_version.py
cspyce/_typemap_samples.cpython-310-darwin.so
cspyce/cspyce2.py
cspyce/typemap_test.py
cspyce/spice_cell.py
cspyce/_cspyce0.cpython-310-darwin.so
cspyce/__init__.py
cspyce/alias_support.py
cspyce/typemap_samples.py
cspyce/aliases.py
cspyce/cspyce0.py
cspyce/record_support.py
cspyce/swig_python_callback.py
cspyce/cspyce1.py
cspyce/array_support.py
cspyce/cspyce1_info.py
cspyce/cspyce0_info.py
