Metadata-Version: 2.1
Name: cspyce
Version: 2.3.2
Summary: High-performance Python interface to the NAIF CSPICE library
Home-page: https://github.com/SETI/rms-cspyce
Maintainer: Robert S. French
Maintainer-email: "Robert S. French" <rfrench@seti.org>
License: Apache-2.0
Project-URL: homepage, https://github.com/SETI/rms-cspyce
Project-URL: Repository, https://github.com/SETI/rms-cspyce
Project-URL: Source, https://github.com/SETI/rms-cspyce
Project-URL: Issues, https://github.com/SETI/rms-cspyce/issues
Keywords: cspyce,spice,cspice,naif,jpl,space,geometry,ephemeris
Classifier: Development Status :: 5 - Production/Stable
Classifier: Natural Language :: English
Classifier: Topic :: Scientific/Engineering
Classifier: Topic :: Scientific/Engineering :: Astronomy
Classifier: License :: OSI Approved :: Apache Software License
Classifier: Programming Language :: Python :: 3.9
Classifier: Programming Language :: Python :: 3.10
Classifier: Programming Language :: Python :: 3.11
Classifier: Programming Language :: Python :: 3.12
Classifier: Programming Language :: Python :: 3.13
Classifier: Operating System :: MacOS :: MacOS X
Classifier: Operating System :: POSIX :: Linux
Classifier: Operating System :: Microsoft :: Windows
Requires-Python: >=3.9
License-File: LICENSE.md
Requires-Dist: numpy
